[
  {
    "id": "test-local-image",
    "donorId": "donor1",
    "donorName": "Testeur Local",
    "title": "Don de test avec image locale",
    "description": "Test pour vérifier l'affichage des images locales",
    "quantity": "1 portion",
    "category": "fruits_legumes",
    "expirationDate": "2024-12-31T23:59:59.000Z",
    "address": "123 Rue de Test, Paris",
    "latitude": 48.8566,
    "longitude": 2.3522,
    "imageUrls": [
      "assets/images/donations/test-image.svg"
    ],
    "status": "disponible",
    "createdAt": "2024-01-20T15:00:00.000Z",
    "updatedAt": "2024-01-20T15:00:00.000Z",
    "notes": "",
    "isUrgent": false
  }
]